intellema_vdk/__init__.py
intellema_vdk/__pycache__/__init__.cpython-312.pyc
intellema_vdk/livekit_lib/__init__.py
intellema_vdk/livekit_lib/client.py
intellema_vdk/livekit_lib/__pycache__/__init__.cpython-312.pyc
intellema_vdk/livekit_lib/__pycache__/client.cpython-312.pyc
intellema_vdk/retell_lib/__init__.py
intellema_vdk/retell_lib/import_phone_number.py
intellema_vdk/retell_lib/retell_client.py
intellema_vdk/retell_lib/__pycache__/__init__.cpython-312.pyc
intellema_vdk/retell_lib/__pycache__/retell_client.cpython-312.pyc
intellema_vdk/speech_lib/__init__.py
intellema_vdk/speech_lib/stt_client.py
intellema_vdk/speech_lib/tts_streamer.py
intellema_vdk/speech_lib/__pycache__/__init__.cpython-312.pyc
intellema_vdk/speech_lib/__pycache__/stt_client.cpython-312.pyc
intellema_vdk/speech_lib/__pycache__/tts_streamer.cpython-312.pyc
intellema_vdk-0.2.1.dist-info/licenses/LICENSE
intellema_vdk-0.2.1.dist-info/METADATA
intellema_vdk-0.2.1.dist-info/WHEEL
intellema_vdk-0.2.1.dist-info/top_level.txt
intellema_vdk-0.2.1.dist-info/RECORD
