Metadata-Version: 2.4
Name: intellema-vdk
Version: 0.2.1
Summary: A Voice Development Kit for different Voice Agent Platforms
Author: Intellema
License: MIT License
Classifier: Programming Language :: Python :: 3
Classifier: License :: OSI Approved :: MIT License
Classifier: Operating System :: OS Independent
Requires-Python: >=3.8
License-File: LICENSE
Requires-Dist: livekit-api>=1.1.0
Requires-Dist: python-dotenv>=1.0.0
Requires-Dist: boto3>=1.28.0
Requires-Dist: twilio
Requires-Dist: retell-sdk
Requires-Dist: requests
Requires-Dist: openai
Requires-Dist: httpx
Requires-Dist: pyaudio
Requires-Dist: together
Requires-Dist: langchain-openai
Requires-Dist: langchain-core
Dynamic: license-file
